{
  "type": "FeatureCollection",
  "features": [
    {
      "type": "Feature",
      "properties": {
        "acroutes": [
          100000,
          510000,
          511300
        ],
        "adcode": 511381,
        "center": [
          105.975266,
          31.580466
        ],
        "centroid": [
          106.072847,
          31.596147
        ],
        "childrenNum": 0,
        "level": "district",
        "name": "阆中市",
        "parent": {
          "adcode": 511300
        },
        "subFeatureIndex": 8
      },
      "geometry": {
        "type": "MultiPolygon",
        "coordinates": [
          [
            [
              [
                105.689296,
                31.597604
              ],
              [
                105.692726,
                31.600456
              ],
              [
                105.695241,
                31.599348
              ],
              [
                105.698182,
                31.594074
              ],
              [
                105.698899,
                31.588121
              ],
              [
                105.7012,
                31.590572
              ],
              [
                105.701932,
                31.594545
              ],
              [
                105.70085,
                31.603114
              ],
              [
                105.69995,
                31.605384
              ],
              [
                105.696917,
                31.608775
              ],
              [
                105.693655,
                31.610381
              ],
              [
                105.689067,
                31.611502
              ],
              [
                105.685729,
                31.613509
              ],
              [
                105.687497,
                31.618796
              ],
              [
                105.688549,
                31.626491
              ],
              [
                105.691963,
                31.630061
              ],
              [
                105.692497,
                31.633549
              ],
              [
                105.694402,
                31.636164
              ],
              [
                105.694753,
                31.640799
              ],
              [
                105.696628,
                31.645559
              ],
              [
                105.698609,
                31.646915
              ],
              [
                105.698838,
                31.649558
              ],
              [
                105.703532,
                31.649987
              ],
              [
                105.704935,
                31.651578
              ],
              [
                105.709477,
                31.652256
              ],
              [
                105.712693,
                31.650291
              ],
              [
                105.714309,
                31.651509
              ],
              [
                105.71472,
                31.654248
              ],
              [
                105.716565,
                31.655714
              ],
              [
                105.717159,
                31.658938
              ],
              [
                105.713669,
                31.661967
              ],
              [
                105.712967,
                31.663794
              ],
              [
                105.715559,
                31.665329
              ],
              [
                105.720055,
                31.665509
              ],
              [
                105.723317,
                31.663558
              ],
              [
                105.726457,
                31.667335
              ],
              [
                105.727143,
                31.67284
              ],
              [
                105.721656,
                31.678304
              ],
              [
                105.721732,
                31.680655
              ],
              [
                105.724414,
                31.684085
              ],
              [
                105.724811,
                31.686948
              ],
              [
                105.722418,
                31.692521
              ],
              [
                105.723454,
                31.696228
              ],
              [
                105.72917,
                31.699062
              ],
              [
                105.7301,
                31.701717
              ],
              [
                105.728621,
                31.706903
              ],
              [
                105.724277,
                31.713152
              ],
              [
                105.723302,
                31.716664
              ],
              [
                105.723271,
                31.722374
              ],
              [
                105.724826,
                31.725733
              ],
              [
                105.726244,
                31.726659
              ],
              [
                105.731472,
                31.72695
              ],
              [
                105.736883,
                31.725913
              ],
              [
                105.741913,
                31.721779
              ],
              [
                105.749412,
                31.718821
              ],
              [
                105.75275,
                31.719443
              ],
              [
                105.755676,
                31.725194
              ],
              [
                105.758679,
                31.729466
              ],
              [
                105.760661,
                31.731069
              ],
              [
                105.765538,
                31.733184
              ],
              [
                105.768587,
                31.735424
              ],
              [
                105.771147,
                31.733792
              ],
              [
                105.771163,
                31.725236
              ],
              [
                105.772199,
                31.722637
              ],
              [
                105.775857,
                31.720176
              ],
              [
                105.780125,
                31.713982
              ],
              [
                105.781101,
                31.711258
              ],
              [
                105.780613,
                31.709309
              ],
              [
                105.778479,
                31.708036
              ],
              [
                105.778174,
                31.706211
              ],
              [
                105.781802,
                31.70516
              ],
              [
                105.787487,
                31.705313
              ],
              [
                105.792075,
                31.704663
              ],
              [
                105.794514,
                31.700459
              ],
              [
                105.796648,
                31.693849
              ],
              [
                105.801998,
                31.687736
              ],
              [
                105.806723,
                31.68533
              ],
              [
                105.808171,
                31.683338
              ],
              [
                105.809558,
                31.678387
              ],
              [
                105.812454,
                31.676257
              ],
              [
                105.816036,
                31.677654
              ],
              [
                105.816768,
                31.676533
              ],
              [
                105.816143,
                31.671581
              ],
              [
                105.81788,
                31.667764
              ],
              [
                105.821234,
                31.666574
              ],
              [
                105.828215,
                31.668704
              ],
              [
                105.832208,
                31.667667
              ],
              [
                105.834495,
                31.664361
              ],
              [
                105.838183,
                31.663946
              ],
              [
                105.842802,
                31.667169
              ],
              [
                105.847131,
                31.667086
              ],
              [
                105.847938,
                31.664375
              ],
              [
                105.841811,
                31.661871
              ],
              [
                105.841445,
                31.657582
              ],
              [
                105.846323,
                31.654137
              ],
              [
                105.847024,
                31.652449
              ],
              [
                105.844158,
                31.649959
              ],
              [
                105.840515,
                31.651647
              ],
              [
                105.837482,
                31.650526
              ],
              [
                105.838488,
                31.648036
              ],
              [
                105.842604,
                31.646846
              ],
              [
                105.844128,
                31.644881
              ],
              [
                105.83858,
                31.642086
              ],
              [
                105.839418,
                31.639748
              ],
              [
                105.843228,
                31.640495
              ],
              [
                105.845637,
                31.639499
              ],
              [
                105.845058,
                31.633881
              ],
              [
                105.84582,
                31.632594
              ],
              [
                105.852633,
                31.631251
              ],
              [
                105.853288,
                31.628082
              ],
              [
                105.851383,
                31.62602
              ],
              [
                105.853014,
                31.62454
              ],
              [
                105.858288,
                31.625135
              ],
              [
                105.859568,
                31.624097
              ],
              [
                105.859401,
                31.619197
              ],
              [
                105.865315,
                31.614768
              ],
              [
                105.867525,
                31.615474
              ],
              [
                105.869232,
                31.619862
              ],
              [
                105.869079,
                31.624664
              ],
              [
                105.875085,
                31.624969
              ],
              [
                105.88577,
                31.629286
              ],
              [
                105.884718,
                31.631279
              ],
              [
                105.881761,
                31.631874
              ],
              [
                105.879963,
                31.635403
              ],
              [
                105.876457,
                31.639706
              ],
              [
                105.877356,
                31.642072
              ],
              [
                105.880999,
                31.642598
              ],
              [
                105.881639,
                31.648077
              ],
              [
                105.886501,
                31.649074
              ],
              [
                105.888757,
                31.648022
              ],
              [
                105.89115,
                31.64502
              ],
              [
                105.896058,
                31.635251
              ],
              [
                105.898025,
                31.633161
              ],
              [
                105.905097,
                31.628581
              ],
              [
                105.910523,
                31.625813
              ],
              [
                105.915233,
                31.625259
              ],
              [
                105.918724,
                31.62602
              ],
              [
                105.919349,
                31.62757
              ],
              [
                105.919273,
                31.633645
              ],
              [
                105.921071,
                31.636662
              ],
              [
                105.92854,
                31.643207
              ],
              [
                105.929531,
                31.644701
              ],
              [
                105.929942,
                31.649198
              ],
              [
                105.925049,
                31.653432
              ],
              [
                105.921025,
                31.655424
              ],
              [
                105.920172,
                31.658813
              ],
              [
                105.922245,
                31.663462
              ],
              [
                105.925065,
                31.664776
              ],
              [
                105.931756,
                31.663614
              ],
              [
                105.938585,
                31.663794
              ],
              [
                105.950001,
                31.66757
              ],
              [
                105.958201,
                31.672467
              ],
              [
                105.962302,
                31.673117
              ],
              [
                105.964801,
                31.672287
              ],
              [
                105.966798,
                31.670267
              ],
              [
                105.969191,
                31.664458
              ],
              [
                105.972179,
                31.662618
              ],
              [
                105.977559,
                31.662466
              ],
              [
                105.983717,
                31.667847
              ],
              [
                105.987269,
                31.667376
              ],
              [
                105.991475,
                31.664983
              ],
              [
                105.992481,
                31.666477
              ],
              [
                105.992146,
                31.669327
              ],
              [
                105.990119,
                31.67284
              ],
              [
                105.990957,
                31.673878
              ],
              [
                106.000895,
                31.676492
              ],
              [
                106.001581,
                31.6806
              ],
              [
                106.00373,
                31.683186
              ],
              [
                106.00719,
                31.684721
              ],
              [
                106.01158,
                31.684057
              ],
              [
                106.028606,
                31.688124
              ],
              [
                106.032447,
                31.687612
              ],
              [
                106.038193,
                31.690571
              ],
              [
                106.042309,
                31.690737
              ],
              [
                106.045433,
                31.692535
              ],
              [
                106.04839,
                31.698094
              ],
              [
                106.051134,
                31.699049
              ],
              [
                106.05813,
                31.698744
              ],
              [
                106.064273,
                31.697154
              ],
              [
                106.078037,
                31.697237
              ],
              [
                106.081542,
                31.698772
              ],
              [
                106.082137,
                31.701233
              ],
              [
                106.080049,
                31.703086
              ],
              [
                106.076177,
                31.704331
              ],
              [
                106.068282,
                31.708424
              ],
              [
                106.068754,
                31.710968
              ],
              [
                106.078235,
                31.714798
              ],
              [
                106.082899,
                31.717424
              ],
              [
                106.098629,
                31.729023
              ],
              [
                106.102226,
                31.732493
              ],
              [
                106.103065,
                31.735216
              ],
              [
                106.100839,
                31.739156
              ],
              [
                106.101495,
                31.741312
              ],
              [
                106.106921,
                31.741298
              ],
              [
                106.109146,
                31.742017
              ],
              [
                106.110183,
                31.744408
              ],
              [
                106.108095,
                31.747642
              ],
              [
                106.108125,
                31.749757
              ],
              [
                106.111143,
                31.753502
              ],
              [
                106.111524,
                31.757109
              ],
              [
                106.112774,
                31.759555
              ],
              [
                106.117377,
                31.762637
              ],
              [
                106.124038,
                31.764102
              ],
              [
                106.128596,
                31.767183
              ],
              [
                106.12887,
                31.769753
              ],
              [
                106.127315,
                31.773401
              ],
              [
                106.126873,
                31.778997
              ],
              [
                106.124876,
                31.78129
              ],
              [
                106.121523,
                31.783432
              ],
              [
                106.122986,
                31.787314
              ],
              [
                106.120868,
                31.788488
              ],
              [
                106.123611,
                31.791997
              ],
              [
                106.116524,
                31.788999
              ],
              [
                106.113871,
                31.790464
              ],
              [
                106.110549,
                31.790781
              ],
              [
                106.114161,
                31.796127
              ],
              [
                106.11538,
                31.801377
              ],
              [
                106.114817,
                31.804139
              ],
              [
                106.119709,
                31.80599
              ],
              [
                106.120197,
                31.808062
              ],
              [
                106.118871,
                31.812288
              ],
              [
                106.120334,
                31.817357
              ],
              [
                106.122194,
                31.820133
              ],
              [
                106.126035,
                31.82353
              ],
              [
                106.126568,
                31.831125
              ],
              [
                106.129053,
                31.834591
              ],
              [
                106.132162,
                31.834688
              ],
              [
                106.130348,
                31.829261
              ],
              [
                106.13393,
                31.823779
              ],
              [
                106.135775,
                31.81494
              ],
              [
                106.137756,
                31.811694
              ],
              [
                106.142116,
                31.81157
              ],
              [
                106.146582,
                31.814249
              ],
              [
                106.151749,
                31.81273
              ],
              [
                106.152389,
                31.811183
              ],
              [
                106.150926,
                31.808338
              ],
              [
                106.152999,
                31.80773
              ],
              [
                106.153364,
                31.805893
              ],
              [
                106.158532,
                31.8107
              ],
              [
                106.161108,
                31.812371
              ],
              [
                106.167921,
                31.815479
              ],
              [
                106.172661,
                31.815258
              ],
              [
                106.176533,
                31.81581
              ],
              [
                106.187019,
                31.821348
              ],
              [
                106.194382,
                31.821873
              ],
              [
                106.19714,
                31.821099
              ],
              [
                106.199183,
                31.8186
              ],
              [
                106.197963,
                31.811377
              ],
              [
                106.194564,
                31.806418
              ],
              [
                106.191928,
                31.804222
              ],
              [
                106.191226,
                31.801349
              ],
              [
                106.191745,
                31.794774
              ],
              [
                106.194503,
                31.785919
              ],
              [
                106.199457,
                31.781967
              ],
              [
                106.207475,
                31.778872
              ],
              [
                106.209517,
                31.772945
              ],
              [
                106.211362,
                31.770748
              ],
              [
                106.214959,
                31.770237
              ],
              [
                106.220812,
                31.775308
              ],
              [
                106.225674,
                31.777919
              ],
              [
                106.232244,
                31.778002
              ],
              [
                106.240855,
                31.773774
              ],
              [
                106.244818,
                31.775432
              ],
              [
                106.245108,
                31.779315
              ],
              [
                106.248217,
                31.782423
              ],
              [
                106.251495,
                31.783031
              ],
              [
                106.254817,
                31.781138
              ],
              [
                106.255701,
                31.7789
              ],
              [
                106.257942,
                31.778375
              ],
              [
                106.262103,
                31.773898
              ],
              [
                106.267834,
                31.776054
              ],
              [
                106.26727,
                31.778016
              ],
              [
                106.269221,
                31.781415
              ],
              [
                106.27195,
                31.783155
              ],
              [
                106.27198,
                31.785559
              ],
              [
                106.275303,
                31.796901
              ],
              [
                106.273428,
                31.801156
              ],
              [
                106.272529,
                31.807938
              ],
              [
                106.270441,
                31.810935
              ],
              [
                106.271493,
                31.812164
              ],
              [
                106.276218,
                31.812896
              ],
              [
                106.281888,
                31.815962
              ],
              [
                106.285378,
                31.81581
              ],
              [
                106.289494,
                31.809319
              ],
              [
                106.292283,
                31.807399
              ],
              [
                106.293838,
                31.808462
              ],
              [
                106.295225,
                31.811487
              ],
              [
                106.298441,
                31.809761
              ],
              [
                106.300865,
                31.810948
              ],
              [
                106.300468,
                31.813821
              ],
              [
                106.302221,
                31.817564
              ],
              [
                106.307678,
                31.823323
              ],
              [
                106.310452,
                31.825574
              ],
              [
                106.319567,
                31.824414
              ],
              [
                106.324018,
                31.826637
              ],
              [
                106.327081,
                31.829357
              ],
              [
                106.327767,
                31.832382
              ],
              [
                106.332584,
                31.838222
              ],
              [
                106.331319,
                31.83999
              ],
              [
                106.333285,
                31.846617
              ],
              [
                106.335556,
                31.848453
              ],
              [
                106.337309,
                31.848274
              ],
              [
                106.342994,
                31.845747
              ],
              [
                106.349228,
                31.848605
              ],
              [
                106.355554,
                31.848425
              ],
              [
                106.361224,
                31.846299
              ],
              [
                106.362002,
                31.843262
              ],
              [
                106.35941,
                31.838471
              ],
              [
                106.359487,
                31.83252
              ],
              [
                106.361605,
                31.830531
              ],
              [
                106.366239,
                31.829841
              ],
              [
                106.370232,
                31.832202
              ],
              [
                106.3729,
                31.831498
              ],
              [
                106.377473,
                31.826623
              ],
              [
                106.376832,
                31.824676
              ],
              [
                106.378631,
                31.821099
              ],
              [
                106.380079,
                31.815755
              ],
              [
                106.380292,
                31.812606
              ],
              [
                106.377991,
                31.807537
              ],
              [
                106.379347,
                31.80523
              ],
              [
                106.384225,
                31.801694
              ],
              [
                106.386145,
                31.801971
              ],
              [
                106.394559,
                31.805907
              ],
              [
                106.397638,
                31.803366
              ],
              [
                106.397516,
                31.799995
              ],
              [
                106.401129,
                31.794387
              ],
              [
                106.40433,
                31.791085
              ],
              [
                106.401601,
                31.789414
              ],
              [
                106.40119,
                31.787687
              ],
              [
                106.404208,
                31.786153
              ],
              [
                106.405839,
                31.782948
              ],
              [
                106.406585,
                31.777035
              ],
              [
                106.411143,
                31.770168
              ],
              [
                106.416356,
                31.766105
              ],
              [
                106.420075,
                31.760163
              ],
              [
                106.424251,
                31.756487
              ],
              [
                106.424221,
                31.754608
              ],
              [
                106.419755,
                31.754787
              ],
              [
                106.411798,
                31.755976
              ],
              [
                106.407683,
                31.755188
              ],
              [
                106.404406,
                31.751291
              ],
              [
                106.405793,
                31.747905
              ],
              [
                106.410183,
                31.744367
              ],
              [
                106.409664,
                31.738174
              ],
              [
                106.406113,
                31.733958
              ],
              [
                106.406509,
                31.729424
              ],
              [
                106.405244,
                31.725678
              ],
              [
                106.401098,
                31.724171
              ],
              [
                106.397425,
                31.727959
              ],
              [
                106.393126,
                31.728139
              ],
              [
                106.389804,
                31.729922
              ],
              [
                106.385764,
                31.728927
              ],
              [
                106.384103,
                31.72959
              ],
              [
                106.383006,
                31.733516
              ],
              [
                106.378753,
                31.732949
              ],
              [
                106.379408,
                31.728913
              ],
              [
                106.382746,
                31.722955
              ],
              [
                106.38264,
                31.720425
              ],
              [
                106.378387,
                31.716318
              ],
              [
                106.37668,
                31.712572
              ],
              [
                106.373159,
                31.711507
              ],
              [
                106.373266,
                31.708258
              ],
              [
                106.367977,
                31.706986
              ],
              [
                106.364288,
                31.705008
              ],
              [
                106.363495,
                31.703072
              ],
              [
                106.364806,
                31.69815
              ],
              [
                106.366468,
                31.69667
              ],
              [
                106.372625,
                31.694955
              ],
              [
                106.377213,
                31.691318
              ],
              [
                106.385856,
                31.687985
              ],
              [
                106.39052,
                31.687543
              ],
              [
                106.399361,
                31.681997
              ],
              [
                106.400107,
                31.678954
              ],
              [
                106.401601,
                31.677322
              ],
              [
                106.400702,
                31.673034
              ],
              [
                106.401083,
                31.670682
              ],
              [
                106.40689,
                31.669396
              ],
              [
                106.408826,
                31.666602
              ],
              [
                106.406524,
                31.663157
              ],
              [
                106.406921,
                31.662023
              ],
              [
                106.406159,
                31.659657
              ],
              [
                106.400931,
                31.657734
              ],
              [
                106.402318,
                31.655106
              ],
              [
                106.398476,
                31.653957
              ],
              [
                106.398431,
                31.652463
              ],
              [
                106.396221,
                31.65202
              ],
              [
                106.395931,
                31.649406
              ],
              [
                106.398751,
                31.647455
              ],
              [
                106.395519,
                31.64668
              ],
              [
                106.390962,
                31.647538
              ],
              [
                106.390474,
                31.646168
              ],
              [
                106.383066,
                31.648396
              ],
              [
                106.376467,
                31.653196
              ],
              [
                106.373205,
                31.654193
              ],
              [
                106.365218,
                31.652532
              ],
              [
                106.360904,
                31.648299
              ],
              [
                106.358801,
                31.639236
              ],
              [
                106.357718,
                31.637423
              ],
              [
                106.354045,
                31.636164
              ],
              [
                106.350859,
                31.63633
              ],
              [
                106.336913,
                31.638655
              ],
              [
                106.329474,
                31.639236
              ],
              [
                106.324124,
                31.640246
              ],
              [
                106.319552,
                31.639416
              ],
              [
                106.31757,
                31.635306
              ],
              [
                106.315833,
                31.634185
              ],
              [
                106.308379,
                31.633991
              ],
              [
                106.303715,
                31.631888
              ],
              [
                106.299645,
                31.633811
              ],
              [
                106.292893,
                31.634517
              ],
              [
                106.288381,
                31.63734
              ],
              [
                106.2864,
                31.637423
              ],
              [
                106.281446,
                31.634752
              ],
              [
                106.275806,
                31.627889
              ],
              [
                106.275364,
                31.626629
              ],
              [
                106.276568,
                31.62263
              ],
              [
                106.274556,
                31.619363
              ],
              [
                106.272575,
                31.618146
              ],
              [
                106.26974,
                31.61863
              ],
              [
                106.264588,
                31.621495
              ],
              [
                106.261478,
                31.621952
              ],
              [
                106.25904,
                31.621163
              ],
              [
                106.252546,
                31.615986
              ],
              [
                106.250915,
                31.613246
              ],
              [
                106.251723,
                31.610962
              ],
              [
                106.253385,
                31.610685
              ],
              [
                106.252744,
                31.608235
              ],
              [
                106.250702,
                31.607502
              ],
              [
                106.247913,
                31.604733
              ],
              [
                106.246038,
                31.606048
              ],
              [
                106.243873,
                31.604124
              ],
              [
                106.243797,
                31.601107
              ],
              [
                106.241618,
                31.599695
              ],
              [
                106.240185,
                31.596635
              ],
              [
                106.24113,
                31.594254
              ],
              [
                106.244864,
                31.592994
              ],
              [
                106.245184,
                31.591139
              ],
              [
                106.247684,
                31.590433
              ],
              [
                106.245931,
                31.588606
              ],
              [
                106.246648,
                31.586113
              ],
              [
                106.249147,
                31.585574
              ],
              [
                106.247257,
                31.580465
              ],
              [
                106.250199,
                31.579592
              ],
              [
                106.252623,
                31.575632
              ],
              [
                106.258658,
                31.575674
              ],
              [
                106.259771,
                31.573874
              ],
              [
                106.264847,
                31.574469
              ],
              [
                106.265197,
                31.571783
              ],
              [
                106.268688,
                31.571312
              ],
              [
                106.272956,
                31.572627
              ],
              [
                106.276218,
                31.57163
              ],
              [
                106.280257,
                31.568155
              ],
              [
                106.279815,
                31.563225
              ],
              [
                106.282116,
                31.557658
              ],
              [
                106.280348,
                31.555151
              ],
              [
                106.277468,
                31.554846
              ],
              [
                106.273367,
                31.557976
              ],
              [
                106.270212,
                31.557408
              ],
              [
                106.268673,
                31.553877
              ],
              [
                106.269542,
                31.550719
              ],
              [
                106.271752,
                31.549181
              ],
              [
                106.276141,
                31.548946
              ],
              [
                106.279236,
                31.547616
              ],
              [
                106.28172,
                31.545026
              ],
              [
                106.286018,
                31.542741
              ],
              [
                106.287253,
                31.539361
              ],
              [
                106.282787,
                31.537255
              ],
              [
                106.275562,
                31.531728
              ],
              [
                106.27291,
                31.528514
              ],
              [
                106.273886,
                31.525328
              ],
              [
                106.27608,
                31.524483
              ],
              [
                106.275334,
                31.522751
              ],
              [
                106.269374,
                31.521601
              ],
              [
                106.267088,
                31.520395
              ],
              [
                106.269084,
                31.513842
              ],
              [
                106.271996,
                31.509533
              ],
              [
                106.272605,
                31.504503
              ],
              [
                106.273916,
                31.503034
              ],
              [
                106.276812,
                31.502452
              ],
              [
                106.281964,
                31.503685
              ],
              [
                106.288213,
                31.500581
              ],
              [
                106.291917,
                31.499639
              ],
              [
                106.292969,
                31.498461
              ],
              [
                106.296551,
                31.486265
              ],
              [
                106.295957,
                31.481871
              ],
              [
                106.296536,
                31.476146
              ],
              [
                106.295225,
                31.47239
              ],
              [
                106.29742,
                31.46819
              ],
              [
                106.300423,
                31.465473
              ],
              [
                106.302816,
                31.460052
              ],
              [
                106.29963,
                31.460066
              ],
              [
                106.29617,
                31.462104
              ],
              [
                106.294432,
                31.46209
              ],
              [
                106.289814,
                31.460149
              ],
              [
                106.288305,
                31.457723
              ],
              [
                106.288747,
                31.451636
              ],
              [
                106.285211,
                31.44652
              ],
              [
                106.286765,
                31.443844
              ],
              [
                106.283427,
                31.44297
              ],
              [
                106.280318,
                31.445619
              ],
              [
                106.278916,
                31.445535
              ],
              [
                106.277635,
                31.44028
              ],
              [
                106.277559,
                31.434914
              ],
              [
                106.275577,
                31.433887
              ],
              [
                106.267027,
                31.433471
              ],
              [
                106.262515,
                31.435621
              ],
              [
                106.26192,
                31.433679
              ],
              [
                106.265899,
                31.431114
              ],
              [
                106.266188,
                31.428146
              ],
              [
                106.265121,
                31.425774
              ],
              [
                106.260427,
                31.425469
              ],
              [
                106.255762,
                31.428396
              ],
              [
                106.249178,
                31.431017
              ],
              [
                106.247211,
                31.432598
              ],
              [
                106.244148,
                31.432112
              ],
              [
                106.239194,
                31.428562
              ],
              [
                106.234652,
                31.424041
              ],
              [
                106.227412,
                31.418535
              ],
              [
                106.224211,
                31.417924
              ],
              [
                106.218434,
                31.419159
              ],
              [
                106.212185,
                31.418146
              ],
              [
                106.210462,
                31.418812
              ],
              [
                106.209151,
                31.422848
              ],
              [
                106.206225,
                31.424568
              ],
              [
                106.197567,
                31.426412
              ],
              [
                106.194976,
                31.424623
              ],
              [
                106.191882,
                31.420379
              ],
              [
                106.187141,
                31.423639
              ],
              [
                106.188605,
                31.430615
              ],
              [
                106.186684,
                31.432584
              ],
              [
                106.18391,
                31.433139
              ],
              [
                106.181029,
                31.430504
              ],
              [
                106.178347,
                31.426718
              ],
              [
                106.176792,
                31.425982
              ],
              [
                106.170908,
                31.427591
              ],
              [
                106.167128,
                31.425178
              ],
              [
                106.166397,
                31.422529
              ],
              [
                106.164628,
                31.421364
              ],
              [
                106.157754,
                31.421628
              ],
              [
                106.15687,
                31.42307
              ],
              [
                106.155742,
                31.429311
              ],
              [
                106.156916,
                31.433194
              ],
              [
                106.156657,
                31.435468
              ],
              [
                106.155178,
                31.435967
              ],
              [
                106.150377,
                31.43533
              ],
              [
                106.148441,
                31.431724
              ],
              [
                106.144874,
                31.42988
              ],
              [
                106.141171,
                31.429782
              ],
              [
                106.135074,
                31.431336
              ],
              [
                106.130912,
                31.430351
              ],
              [
                106.127712,
                31.425026
              ],
              [
                106.126675,
                31.421073
              ],
              [
                106.124252,
                31.41773
              ],
              [
                106.12131,
                31.41712
              ],
              [
                106.118719,
                31.418812
              ],
              [
                106.117423,
                31.418382
              ],
              [
                106.110838,
                31.411932
              ],
              [
                106.107698,
                31.412556
              ],
              [
                106.104757,
                31.41171
              ],
              [
                106.095062,
                31.405912
              ],
              [
                106.088737,
                31.407258
              ],
              [
                106.081009,
                31.402846
              ],
              [
                106.074348,
                31.403221
              ],
              [
                106.068495,
                31.400544
              ],
              [
                106.053176,
                31.398255
              ],
              [
                106.046988,
                31.39881
              ],
              [
                106.044869,
                31.400516
              ],
              [
                106.040327,
                31.411128
              ],
              [
                106.039321,
                31.418299
              ],
              [
                106.036745,
                31.419575
              ],
              [
                106.031197,
                31.419145
              ],
              [
                106.021579,
                31.416995
              ],
              [
                106.016869,
                31.417841
              ],
              [
                106.011367,
                31.417924
              ],
              [
                106.006382,
                31.423347
              ],
              [
                106.003944,
                31.424277
              ],
              [
                105.992375,
                31.42644
              ],
              [
                105.987802,
                31.423444
              ],
              [
                105.983717,
                31.423264
              ],
              [
                105.984434,
                31.420587
              ],
              [
                105.982162,
                31.412931
              ],
              [
                105.979739,
                31.410143
              ],
              [
                105.975059,
                31.409838
              ],
              [
                105.972865,
                31.412501
              ],
              [
                105.970593,
                31.411891
              ],
              [
                105.966691,
                31.409186
              ],
              [
                105.965228,
                31.411696
              ],
              [
                105.961479,
                31.411738
              ],
              [
                105.959299,
                31.410628
              ],
              [
                105.95939,
                31.40576
              ],
              [
                105.957592,
                31.402
              ],
              [
                105.950474,
                31.399364
              ],
              [
                105.950321,
                31.395799
              ],
              [
                105.951708,
                31.39043
              ],
              [
                105.948629,
                31.384464
              ],
              [
                105.949559,
                31.381439
              ],
              [
                105.948645,
                31.379358
              ],
              [
                105.951708,
                31.377054
              ],
              [
                105.947943,
                31.374529
              ],
              [
                105.944727,
                31.374307
              ],
              [
                105.938569,
                31.368021
              ],
              [
                105.935826,
                31.366869
              ],
              [
                105.9361,
                31.364343
              ],
              [
                105.938386,
                31.363816
              ],
              [
                105.936573,
                31.362386
              ],
              [
                105.933859,
                31.362483
              ],
              [
                105.932869,
                31.365384
              ],
              [
                105.93011,
                31.366702
              ],
              [
                105.926086,
                31.365023
              ],
              [
                105.922595,
                31.365759
              ],
              [
                105.917611,
                31.362914
              ],
              [
                105.914989,
                31.363566
              ],
              [
                105.907612,
                31.368159
              ],
              [
                105.905554,
                31.371226
              ],
              [
                105.906256,
                31.376166
              ],
              [
                105.904228,
                31.377443
              ],
              [
                105.89929,
                31.376028
              ],
              [
                105.896119,
                31.373669
              ],
              [
                105.89115,
                31.368326
              ],
              [
                105.889321,
                31.367715
              ],
              [
                105.884017,
                31.370505
              ],
              [
                105.882569,
                31.374126
              ],
              [
                105.886136,
                31.377776
              ],
              [
                105.886669,
                31.380121
              ],
              [
                105.890434,
                31.386531
              ],
              [
                105.896119,
                31.38839
              ],
              [
                105.90179,
                31.388876
              ],
              [
                105.903207,
                31.391692
              ],
              [
                105.900966,
                31.393565
              ],
              [
                105.89615,
                31.394065
              ],
              [
                105.891836,
                31.392927
              ],
              [
                105.888788,
                31.393676
              ],
              [
                105.88798,
                31.396729
              ],
              [
                105.887889,
                31.401861
              ],
              [
                105.88609,
                31.405052
              ],
              [
                105.880176,
                31.410351
              ],
              [
                105.873469,
                31.410906
              ],
              [
                105.872539,
                31.406495
              ],
              [
                105.868851,
                31.402236
              ],
              [
                105.875115,
                31.397727
              ],
              [
                105.874109,
                31.39573
              ],
              [
                105.870345,
                31.393094
              ],
              [
                105.867205,
                31.393343
              ],
              [
                105.863181,
                31.397755
              ],
              [
                105.860833,
                31.401348
              ],
              [
                105.862906,
                31.407591
              ],
              [
                105.862586,
                31.41343
              ],
              [
                105.859553,
                31.419422
              ],
              [
                105.856306,
                31.419935
              ],
              [
                105.854172,
                31.421836
              ],
              [
                105.849859,
                31.421198
              ],
              [
                105.846963,
                31.422446
              ],
              [
                105.84111,
                31.422113
              ],
              [
                105.837878,
                31.419686
              ],
              [
                105.833458,
                31.422765
              ],
              [
                105.828184,
                31.424471
              ],
              [
                105.826142,
                31.426204
              ],
              [
                105.826005,
                31.432625
              ],
              [
                105.82852,
                31.43379
              ],
              [
                105.837177,
                31.433513
              ],
              [
                105.840912,
                31.43429
              ],
              [
                105.84271,
                31.435857
              ],
              [
                105.84332,
                31.438464
              ],
              [
                105.840302,
                31.442499
              ],
              [
                105.837878,
                31.448114
              ],
              [
                105.834921,
                31.452621
              ],
              [
                105.831355,
                31.456239
              ],
              [
                105.82826,
                31.457695
              ],
              [
                105.824221,
                31.457972
              ],
              [
                105.825075,
                31.454257
              ],
              [
                105.829617,
                31.451387
              ],
              [
                105.827742,
                31.44939
              ],
              [
                105.819801,
                31.449154
              ],
              [
                105.812866,
                31.447782
              ],
              [
                105.807851,
                31.445951
              ],
              [
                105.806403,
                31.447712
              ],
              [
                105.803522,
                31.448683
              ],
              [
                105.802486,
                31.450666
              ],
              [
                105.803751,
                31.456808
              ],
              [
                105.802349,
                31.460177
              ],
              [
                105.802882,
                31.463338
              ],
              [
                105.808994,
                31.470033
              ],
              [
                105.813704,
                31.472709
              ],
              [
                105.820395,
                31.474247
              ],
              [
                105.822072,
                31.476174
              ],
              [
                105.820075,
                31.479057
              ],
              [
                105.814939,
                31.480457
              ],
              [
                105.811784,
                31.483077
              ],
              [
                105.80372,
                31.498766
              ],
              [
                105.801251,
                31.500248
              ],
              [
                105.799666,
                31.502576
              ],
              [
                105.800123,
                31.505736
              ],
              [
                105.805412,
                31.515241
              ],
              [
                105.807196,
                31.519176
              ],
              [
                105.810153,
                31.520132
              ],
              [
                105.817454,
                31.516821
              ],
              [
                105.819572,
                31.517915
              ],
              [
                105.817103,
                31.520908
              ],
              [
                105.817576,
                31.522335
              ],
              [
                105.824054,
                31.520783
              ],
              [
                105.826706,
                31.521227
              ],
              [
                105.831797,
                31.529027
              ],
              [
                105.83041,
                31.538821
              ],
              [
                105.829145,
                31.542588
              ],
              [
                105.826569,
                31.547478
              ],
              [
                105.828459,
                31.553461
              ],
              [
                105.828321,
                31.55666
              ],
              [
                105.825715,
                31.559776
              ],
              [
                105.823048,
                31.559513
              ],
              [
                105.818429,
                31.556771
              ],
              [
                105.813887,
                31.563419
              ],
              [
                105.811662,
                31.564873
              ],
              [
                105.809939,
                31.563876
              ],
              [
                105.808156,
                31.55979
              ],
              [
                105.806052,
                31.558045
              ],
              [
                105.804528,
                31.554472
              ],
              [
                105.801388,
                31.554486
              ],
              [
                105.794514,
                31.560067
              ],
              [
                105.790764,
                31.56076
              ],
              [
                105.786557,
                31.559956
              ],
              [
                105.785201,
                31.558281
              ],
              [
                105.789042,
                31.553918
              ],
              [
                105.788737,
                31.55209
              ],
              [
                105.786115,
                31.549472
              ],
              [
                105.781954,
                31.547589
              ],
              [
                105.777869,
                31.54673
              ],
              [
                105.7738,
                31.547672
              ],
              [
                105.768998,
                31.553281
              ],
              [
                105.766453,
                31.555511
              ],
              [
                105.761011,
                31.557741
              ],
              [
                105.749031,
                31.556259
              ],
              [
                105.736456,
                31.557367
              ],
              [
                105.72917,
                31.557533
              ],
              [
                105.724414,
                31.565634
              ],
              [
                105.722082,
                31.567185
              ],
              [
                105.714583,
                31.564263
              ],
              [
                105.71315,
                31.56515
              ],
              [
                105.714553,
                31.571769
              ],
              [
                105.713638,
                31.573874
              ],
              [
                105.707328,
                31.574164
              ],
              [
                105.70402,
                31.574968
              ],
              [
                105.703441,
                31.577141
              ],
              [
                105.704858,
                31.579675
              ],
              [
                105.704538,
                31.582015
              ],
              [
                105.702511,
                31.582735
              ],
              [
                105.693503,
                31.582984
              ],
              [
                105.691933,
                31.584604
              ],
              [
                105.693472,
                31.590987
              ],
              [
                105.692969,
                31.592814
              ],
              [
                105.686979,
                31.59341
              ],
              [
                105.685928,
                31.595043
              ],
              [
                105.689296,
                31.597604
              ]
            ]
          ]
        ]
      }
    }
  ]
}